smuport_ts_middleground_server/__init__.py
smuport_ts_middleground_server/manage.py
smuport_ts_middleground_server/data_apps/__init__.py
smuport_ts_middleground_server/data_apps/urls.py
smuport_ts_middleground_server/data_apps/direct/__init__.py
smuport_ts_middleground_server/data_apps/direct/admin.py
smuport_ts_middleground_server/data_apps/direct/apps.py
smuport_ts_middleground_server/data_apps/direct/filter.py
smuport_ts_middleground_server/data_apps/direct/models.py
smuport_ts_middleground_server/data_apps/direct/serializer.py
smuport_ts_middleground_server/data_apps/direct/tests.py
smuport_ts_middleground_server/data_apps/direct/views.py
smuport_ts_middleground_server/data_apps/direct/migrations/0001_initial.py
smuport_ts_middleground_server/data_apps/direct/migrations/0002_tlmswmsentdetails_wms_ent_plan.py
smuport_ts_middleground_server/data_apps/direct/migrations/0003_auto_20201203_2026.py
smuport_ts_middleground_server/data_apps/direct/migrations/0004_auto_20201203_2027.py
smuport_ts_middleground_server/data_apps/direct/migrations/0005_auto_20201203_2030.py
smuport_ts_middleground_server/data_apps/direct/migrations/0006_auto_20201203_2123.py
smuport_ts_middleground_server/data_apps/direct/migrations/0007_auto_20201203_2124.py
smuport_ts_middleground_server/data_apps/direct/migrations/__init__.py
smuport_ts_middleground_server/data_apps/tlms_wms_public_table/__init__.py
smuport_ts_middleground_server/data_apps/tlms_wms_public_table/admin.py
smuport_ts_middleground_server/data_apps/tlms_wms_public_table/apps.py
smuport_ts_middleground_server/data_apps/tlms_wms_public_table/filters.py
smuport_ts_middleground_server/data_apps/tlms_wms_public_table/models.py
smuport_ts_middleground_server/data_apps/tlms_wms_public_table/serializer.py
smuport_ts_middleground_server/data_apps/tlms_wms_public_table/tests.py
smuport_ts_middleground_server/data_apps/tlms_wms_public_table/views.py
smuport_ts_middleground_server-11.0.0.dist-info/LICENSE.txt
smuport_ts_middleground_server-11.0.0.dist-info/METADATA
smuport_ts_middleground_server-11.0.0.dist-info/WHEEL
smuport_ts_middleground_server-11.0.0.dist-info/top_level.txt
smuport_ts_middleground_server-11.0.0.dist-info/RECORD
